Workbook

Sheet Assumptions
A1: JG MART — FINANCIAL MODEL v1.1
A2: Founder: Fahad Ibrahim | Contact: +8801670-944800 | Japan Garden City, Dhaka
A3: All figures in BDT | Blue text = Inputs (change these) | Black text = Formulas
A5: KEY OPERATING ASSUMPTIONS
A6: Metric | B6: Value | C6: Unit
A7: Average Order Value (AOV) | B7: 800 | C7: BDT
A8: Commission Rate (avg) | B8: 0.11 | C8: %
A9: Delivery Fee (after free period) | B9: 30 | C9: BDT
A10: Subscription Revenue (blended per order) | B10: 20 | C10: BDT
A11: Rider Cost per Order | B11: 31 | C11: BDT
A12: Manager / Ops Cost per Order | B12: 16 | C12: BDT
A13: Marketing / Referral Cost per Order | B13: 13 | C13: BDT
A14: Packaging & Misc per Order | B14: 7 | C14: BDT
A15: Target Orders Month 1 | B15: 150 | C15: orders
A16: Target Orders Month 2 | B16: 350 | C16: orders
A17: Target Orders Month 3 | B17: 550 | C17: orders
A18: Target Orders Month 6 | B18: 900 | C18: orders
A19: Target Orders Month 12 | B19: 1500 | C19: orders
A22: REVENUE PER ORDER CALCULATION
A23: Commission Revenue | B23: =B7*B8
A24: Delivery Fee | B24: =B9
A25: Subscription (blended) | B25: =B10
A26: TOTAL REVENUE PER ORDER | B26: =B23+B24+B25
A28: COST PER ORDER
A29: Rider | B29: =B11
A30: Manager/Ops | B30: =B12
A31: Marketing | B31: =B13
A32: Packaging | B32: =B14
A33: TOTAL COST PER ORDER | B33: =B29+B30+B31+B32
A35: CONTRIBUTION MARGIN PER ORDER | B35: =B26-B33
A36: Contribution Margin % | B36: =B35/B26

Sheet P&L_Projection
A1: JG MART — 12-MONTH P&L PROJECTION
A2: All figures in BDT | Linked to Assumptions sheet
A4: Metric | B4: Month 1 | C4: Month 2 | D4: Month 3 | E4: Month 4 | F4: Month 5 | G4: Month 6 | H4: Month 7 | I4: Month 8 | J4: Month 9 | K4: Month 10 | L4: Month 11 | M4: Month 12
A5: Orders | B5: ='Assumptions'!B15 | C5: ='Assumptions'!B16 | D5: ='Assumptions'!B17 | E5: 650 | F5: 780 | G5: ='Assumptions'!B18 | H5: 1050 | I5: 1150 | J5: 1250 | K5: 1350 | L5: 1400 | M5: ='Assumptions'!B19
A6: Revenue | B6: =B5*Assumptions!$B$26 | C6: =C5*Assumptions!$B$26 | D6: =D5*Assumptions!$B$26 | E6: =E5*Assumptions!$B$26 | F6: =F5*Assumptions!$B$26 | G6: =G5*Assumptions!$B$26 | H6: =H5*Assumptions!$B$26 | I6: =I5*Assumptions!$B$26 | ... M6: =M5*Assumptions!$B$26
A7: Total Costs | B7: =B5*Assumptions!$B$33 | C7: =C5*Assumptions!$B$33 | D7: =D5*Assumptions!$B$33 | E7: =E5*Assumptions!$B$33 | F7: =F5*Assumptions!$B$33 | G7: =G5*Assumptions!$B$33 | H7: =H5*Assumptions!$B$33 | I7: =I5*Assumptions!$B$33 | ... M7: =M5*Assumptions!$B$33
A8: Contribution Profit | B8: =B6-B7 | C8: =C6-C7 | D8: =D6-D7 | E8: =E6-E7 | F8: =F6-F7 | G8: =G6-G7 | H8: =H6-H7 | I8: =I6-I7 | ... M8: =M6-M7
A9: Cumulative Profit | B9: =B8 | C9: =B9+C8 | D9: =C9+D8 | E9: =D9+E8 | F9: =E9+F8 | G9: =F9+G8 | H9: =G9+H8 | I9: =H9+I8 | J9: =I9+J8 | ... M9: =L9+M8
A11: NOTES
A12: • Month 1 assumes free delivery (delivery fee revenue = 0 in early weeks) — adjust manually if needed
A13: • Fixed costs (rent, software, etc.) currently absorbed in per-order manager cost for simplicity
A14: • Seed capital of 1,500,000 BDT provides runway; model shows operating contribution only
A15: • Change yellow cells on Assumptions sheet to run scenarios

Sheet Unit_Economics
A1: JG MART — UNIT ECONOMICS DASHBOARD
A3: Per Order Economics (from Assumptions)
A4: Average Order Value | B4: ='Assumptions'!B7
A5: Revenue per Order | B5: ='Assumptions'!B26
A6: Cost per Order | B6: ='Assumptions'!B33
A7: Contribution per Order | B7: ='Assumptions'!B35
A8: Margin % | B8: ='Assumptions'!B36
A10: Break-even Orders per Month (approx) | B10: 50
A12: SEED CAPITAL USE OF FUNDS
A13: Item | B13: Amount (BDT)
A14: Rider salary (6 months) | B14: 72000
A15: Manager / Founder support (6 months) | B15: 72000
A16: Marketing & Referrals | B16: 50000
A17: Working Capital / Partner float | B17: 50000
A18: Tools, bags, packaging, misc | B18: 6000
A19: TOTAL SEED | B19: =SUM(B14:B18)

Sheet Scenarios
A1: SCENARIO ANALYSIS
A2: Change the yellow cells below to stress-test the model
A4: Scenario | B4: Orders M3 | C4: AOV | D4: Contribution / Order | E4: Monthly Contribution M3
A5: Base Case | B5: 550 | C5: 800 | D5: 71 | E5: =B5*D5
A6: Optimistic | B6: 800 | C6: 900 | D6: 85 | E6: =B6*D6
A7: Pessimistic | B7: 300 | C7: 700 | D7: 45 | E7: =B7*D7
